showFlodersTree.py
pwjyyds-0.1.0.dist-info/LICENSE.txt
pwjyyds-0.1.0.dist-info/METADATA
pwjyyds-0.1.0.dist-info/WHEEL
pwjyyds-0.1.0.dist-info/top_level.txt
pwjyyds-0.1.0.dist-info/RECORD
