Metadata-Version: 2.1
Name: pwjyyds
Version: 0.1.0
Summary: This project is used to display the tree structure of folders.
Home-page: https://github.com/pwjyyds/pwjyyds
Author: Pei
Author-email: p747289013@gmail.com
License: MIT
Platform: UNKNOWN
Classifier: License :: OSI Approved :: MIT License
Classifier: Programming Language :: Python
Classifier: Programming Language :: Python :: 3
Classifier: Programming Language :: Python :: 3.6
Classifier: Programming Language :: Python :: Implementation :: CPython
Classifier: Programming Language :: Python :: Implementation :: PyPy
Requires-Python: >=3.6.0
Requires-Dist: pathlib
Requires-Dist: typing
Requires-Dist: toDocx
